visface/__init__.py
visface/main.so
visface/app/__init__.py
visface/app/common.so
visface/app/face_analysis.so
visface/model_zoo/__init__.py
visface/model_zoo/arcface.so
visface/model_zoo/model_zoo.so
visface/model_zoo/retinaface.so
visface/utils/__init__.py
visface/utils/face_align.so
visface-1.0.7.dist-info/METADATA
visface-1.0.7.dist-info/WHEEL
visface-1.0.7.dist-info/top_level.txt
visface-1.0.7.dist-info/RECORD
