Metadata-Version: 2.1
Name: visface
Version: 1.0.7
Summary: visface
License: Apache License 2.0
Requires-Dist: onnx==1.12.0
Requires-Dist: pyyaml
Requires-Dist: scikit-learn
Requires-Dist: scikit-image
